<?xml version="1.0" encoding="UTF-8"?>
<caaml:SnowProfile xmlns:caaml="http://caaml.org/Schemas/SnowProfileIACS/v6.0.3" xmlns:gml="http://www.opengis.net/gml" xmlns:snowpilot="http://www.snowpilot.org/Schemas/caaml" gml:id="SnowPilot-50920">
  <caaml:metaData>
    <caaml:comment>Observers: Ben Westerik, Brandon Exner&#13;
HS: 390&#13;
Open planar alpine slope</caaml:comment>
    <caaml:customData/>
  </caaml:metaData>
  <caaml:timeRef>
    <caaml:recordTime>
      <caaml:TimeInstant>
        <caaml:timePosition>2023-02-14T11:10:00</caaml:timePosition>
      </caaml:TimeInstant>
    </caaml:recordTime>
    <caaml:dateTimeReport>2023-02-14T14:39:31-09:00</caaml:dateTimeReport>
    <caaml:dateTimeLastEdit>2023-02-14T14:40:38-09:00</caaml:dateTimeLastEdit>
  </caaml:timeRef>
  <caaml:srcRef>
    <caaml:Person gml:id="SnowPilot-User-12586">
      <caaml:name>bmwesterik</caaml:name>
    </caaml:Person>
  </caaml:srcRef>
  <caaml:locRef gml:id="location-nid-50920">
    <caaml:name>Pass Peak</caaml:name>
    <caaml:obsPointSubType>SnowPilot Snowpit site</caaml:obsPointSubType>
    <caaml:validElevation>
      <caaml:ElevationPosition uom="m">
        <caaml:position>1580</caaml:position>
      </caaml:ElevationPosition>
    </caaml:validElevation>
    <caaml:validAspect>
      <caaml:AspectPosition>
        <caaml:position>SE</caaml:position>
      </caaml:AspectPosition>
    </caaml:validAspect>
    <caaml:validSlopeAngle>
      <caaml:SlopeAnglePosition uom="deg">
        <caaml:position>30</caaml:position>
      </caaml:SlopeAnglePosition>
    </caaml:validSlopeAngle>
    <caaml:pointLocation>
      <gml:Point gml:id="pointID" srsDimension="2" srsName="urn:ogc:def:crs:OGC:1.3:CRS84">
        <gml:pos>54.0690740 -127.9813610</gml:pos>
      </gml:Point>
    </caaml:pointLocation>
    <caaml:country>CA</caaml:country>
    <caaml:region>BC</caaml:region>
  </caaml:locRef>
  <caaml:snowProfileResultsOf>
    <caaml:SnowProfileMeasurements dir="top down">
      <caaml:metaData/>
      <caaml:profileDepth uom="cm">210</caaml:profileDepth>
      <caaml:weatherCond>
        <caaml:skyCond>FEW</caaml:skyCond>
        <caaml:precipTI>Nil</caaml:precipTI>
        <caaml:airTempPres uom="degC">-6.5</caaml:airTempPres>
        <caaml:windSpd uom="">M</caaml:windSpd>
        <caaml:windDir>
          <caaml:AspectPosition>
            <caaml:position>SW</caaml:position>
          </caaml:AspectPosition>
        </caaml:windDir>
      </caaml:weatherCond>
      <caaml:snowPackCond>
        <caaml:hS>
          <caaml:Components>
            <caaml:height uom="cm">390</caaml:height>
          </caaml:Components>
        </caaml:hS>
      </caaml:snowPackCond>
      <caaml:surfCond>
        <caaml:metaData>
          <caaml:customData>
            <snowpilot:windLoading>yes</snowpilot:windLoading>
          </caaml:customData>
        </caaml:metaData>
        <caaml:penetrationFoot uom="cm">30</caaml:penetrationFoot>
      </caaml:surfCond>
      <caaml:stratProfile>
        <caaml:Layer>
          <caaml:depthTop uom="cm">0</caaml:depthTop>
          <caaml:thickness uom="cm">200</caaml:thickness>
          <caaml:hardnessTop uom="">P</caaml:hardnessTop>
          <caaml:hardnessBottom uom="">1F</caaml:hardnessBottom>
        </caaml:Layer>
        <caaml:Layer>
          <caaml:metaData>
            <caaml:comment>Jan 28th</caaml:comment>
          </caaml:metaData>
          <caaml:depthTop uom="cm">200</caaml:depthTop>
          <caaml:thickness uom="cm">10</caaml:thickness>
          <caaml:grainFormPrimary>MFcr</caaml:grainFormPrimary>
          <caaml:hardness uom="">K-</caaml:hardness>
        </caaml:Layer>
      </caaml:stratProfile>
      <caaml:stbTests/>
    </caaml:SnowProfileMeasurements>
  </caaml:snowProfileResultsOf>
  <caaml:application>SnowPilot</caaml:application>
  <caaml:applicationVersion>7.91-0.1</caaml:applicationVersion>
</caaml:SnowProfile>
