<?xml version="1.0" encoding="UTF-8"?>
<caaml:SnowProfile xmlns:caaml="http://caaml.org/Schemas/SnowProfileIACS/v6.0.3" xmlns:gml="http://www.opengis.net/gml" xmlns:snowpilot="http://www.snowpilot.org/Schemas/caaml" gml:id="SnowPilot-48772">
  <caaml:metaData>
    <caaml:customData/>
  </caaml:metaData>
  <caaml:timeRef>
    <caaml:recordTime>
      <caaml:TimeInstant>
        <caaml:timePosition>2023-01-17T13:30:00</caaml:timePosition>
      </caaml:TimeInstant>
    </caaml:recordTime>
    <caaml:dateTimeReport>2023-01-17T14:02:31-09:00</caaml:dateTimeReport>
    <caaml:dateTimeLastEdit>2023-01-17T14:02:37-09:00</caaml:dateTimeLastEdit>
  </caaml:timeRef>
  <caaml:srcRef>
    <caaml:Operation gml:id="SnowPilot-Group-1033">
      <caaml:name>ACMG</caaml:name>
      <caaml:contactPerson gml:id="SnowPilot-User-13803">
        <caaml:name>martylazarski</caaml:name>
      </caaml:contactPerson>
    </caaml:Operation>
  </caaml:srcRef>
  <caaml:locRef gml:id="location-nid-48772">
    <caaml:name>3G's</caaml:name>
    <caaml:obsPointSubType>SnowPilot Snowpit site</caaml:obsPointSubType>
    <caaml:validElevation>
      <caaml:ElevationPosition uom="m">
        <caaml:position>2113</caaml:position>
      </caaml:ElevationPosition>
    </caaml:validElevation>
    <caaml:validAspect>
      <caaml:AspectPosition>
        <caaml:position>W</caaml:position>
      </caaml:AspectPosition>
    </caaml:validAspect>
    <caaml:validSlopeAngle>
      <caaml:SlopeAnglePosition uom="deg">
        <caaml:position>20</caaml:position>
      </caaml:SlopeAnglePosition>
    </caaml:validSlopeAngle>
    <caaml:country>CA</caaml:country>
    <caaml:region>BC</caaml:region>
  </caaml:locRef>
  <caaml:snowProfileResultsOf>
    <caaml:SnowProfileMeasurements dir="top down">
      <caaml:metaData/>
      <caaml:profileDepth uom="cm">115</caaml:profileDepth>
      <caaml:weatherCond>
        <caaml:skyCond>OVC</caaml:skyCond>
        <caaml:precipTI>-SN</caaml:precipTI>
      </caaml:weatherCond>
      <caaml:snowPackCond>
        <caaml:hS>
          <caaml:Components>
            <caaml:height uom="cm">115</caaml:height>
          </caaml:Components>
        </caaml:hS>
      </caaml:snowPackCond>
      <caaml:surfCond>
        <caaml:metaData>
          <caaml:customData/>
        </caaml:metaData>
        <caaml:penetrationFoot uom="cm">25</caaml:penetrationFoot>
        <caaml:penetrationSki uom="cm">35</caaml:penetrationSki>
      </caaml:surfCond>
      <caaml:stratProfile>
        <caaml:Layer>
          <caaml:depthTop uom="cm">0</caaml:depthTop>
          <caaml:thickness uom="cm">5</caaml:thickness>
          <caaml:hardness uom="">F</caaml:hardness>
        </caaml:Layer>
        <caaml:Layer>
          <caaml:depthTop uom="cm">5</caaml:depthTop>
          <caaml:thickness uom="cm">15</caaml:thickness>
          <caaml:hardness uom="">1F</caaml:hardness>
        </caaml:Layer>
        <caaml:Layer>
          <caaml:depthTop uom="cm">20</caaml:depthTop>
          <caaml:thickness uom="cm">15</caaml:thickness>
          <caaml:hardness uom="">1F+</caaml:hardness>
        </caaml:Layer>
        <caaml:Layer>
          <caaml:depthTop uom="cm">35</caaml:depthTop>
          <caaml:thickness uom="cm">2</caaml:thickness>
          <caaml:hardness uom="">K</caaml:hardness>
        </caaml:Layer>
        <caaml:Layer>
          <caaml:depthTop uom="cm">37</caaml:depthTop>
          <caaml:thickness uom="cm">13</caaml:thickness>
          <caaml:hardness uom="">P</caaml:hardness>
        </caaml:Layer>
        <caaml:Layer>
          <caaml:depthTop uom="cm">50</caaml:depthTop>
          <caaml:thickness uom="cm">20</caaml:thickness>
          <caaml:hardness uom="">1F+</caaml:hardness>
        </caaml:Layer>
        <caaml:Layer>
          <caaml:depthTop uom="cm">70</caaml:depthTop>
          <caaml:thickness uom="cm">15</caaml:thickness>
          <caaml:hardness uom="">4F</caaml:hardness>
        </caaml:Layer>
        <caaml:Layer>
          <caaml:depthTop uom="cm">85</caaml:depthTop>
          <caaml:thickness uom="cm">30</caaml:thickness>
          <caaml:hardness uom="">F</caaml:hardness>
        </caaml:Layer>
      </caaml:stratProfile>
      <caaml:stbTests>
        <caaml:ComprTest>
          <caaml:failedOn>
            <caaml:Layer>
              <caaml:metaData>
                <caaml:comment>RP</caaml:comment>
              </caaml:metaData>
              <caaml:depthTop uom="cm">95</caaml:depthTop>
            </caaml:Layer>
            <caaml:Results>
              <caaml:testScore>16</caaml:testScore>
            </caaml:Results>
          </caaml:failedOn>
        </caaml:ComprTest>
        <caaml:ComprTest>
          <caaml:failedOn>
            <caaml:Layer>
              <caaml:metaData>
                <caaml:comment>SC</caaml:comment>
              </caaml:metaData>
              <caaml:depthTop uom="cm">15</caaml:depthTop>
            </caaml:Layer>
            <caaml:Results>
              <caaml:testScore>19</caaml:testScore>
            </caaml:Results>
          </caaml:failedOn>
        </caaml:ComprTest>
        <caaml:ComprTest>
          <caaml:failedOn>
            <caaml:Layer>
              <caaml:metaData>
                <caaml:comment>SC DH F 2-3</caaml:comment>
              </caaml:metaData>
              <caaml:depthTop uom="cm">20</caaml:depthTop>
            </caaml:Layer>
            <caaml:Results>
              <caaml:testScore>25</caaml:testScore>
            </caaml:Results>
          </caaml:failedOn>
        </caaml:ComprTest>
        <caaml:ExtColumnTest>
          <caaml:failedOn>
            <caaml:Layer>
              <caaml:depthTop uom="cm">95</caaml:depthTop>
            </caaml:Layer>
            <caaml:Results>
              <caaml:testScore>ECTN21</caaml:testScore>
            </caaml:Results>
          </caaml:failedOn>
        </caaml:ExtColumnTest>
      </caaml:stbTests>
    </caaml:SnowProfileMeasurements>
  </caaml:snowProfileResultsOf>
  <caaml:application>SnowPilot</caaml:application>
  <caaml:applicationVersion>7.91-0.1</caaml:applicationVersion>
</caaml:SnowProfile>
