<?xml version="1.0" encoding="UTF-8"?>
<caaml:SnowProfile xmlns:caaml="http://caaml.org/Schemas/SnowProfileIACS/v6.0.3" xmlns:gml="http://www.opengis.net/gml" xmlns:snowpilot="http://www.snowpilot.org/Schemas/caaml" gml:id="SnowPilot-54498">
  <caaml:metaData>
    <caaml:customData/>
  </caaml:metaData>
  <caaml:timeRef>
    <caaml:recordTime>
      <caaml:TimeInstant>
        <caaml:timePosition>2023-04-17T12:00:00</caaml:timePosition>
      </caaml:TimeInstant>
    </caaml:recordTime>
    <caaml:dateTimeReport>2023-04-18T18:04:52-08:00</caaml:dateTimeReport>
    <caaml:dateTimeLastEdit>2023-04-18T18:05:27-08:00</caaml:dateTimeLastEdit>
  </caaml:timeRef>
  <caaml:srcRef>
    <caaml:Operation gml:id="SnowPilot-Group-647">
      <caaml:name>Tordrillo Mountain Lodge</caaml:name>
      <caaml:contactPerson gml:id="SnowPilot-User-6118">
        <caaml:name>Hugh Barnard</caaml:name>
      </caaml:contactPerson>
    </caaml:Operation>
  </caaml:srcRef>
  <caaml:locRef gml:id="location-nid-54498">
    <caaml:name>The Claw</caaml:name>
    <caaml:obsPointSubType>SnowPilot Snowpit site</caaml:obsPointSubType>
    <caaml:validElevation>
      <caaml:ElevationPosition uom="m">
        <caaml:position>1335</caaml:position>
      </caaml:ElevationPosition>
    </caaml:validElevation>
    <caaml:validAspect>
      <caaml:AspectPosition>
        <caaml:position>N</caaml:position>
      </caaml:AspectPosition>
    </caaml:validAspect>
    <caaml:validSlopeAngle>
      <caaml:SlopeAnglePosition uom="deg">
        <caaml:position>30</caaml:position>
      </caaml:SlopeAnglePosition>
    </caaml:validSlopeAngle>
    <caaml:pointLocation>
      <gml:Point gml:id="pointID" srsDimension="2" srsName="urn:ogc:def:crs:OGC:1.3:CRS84">
        <gml:pos>61.6748660 -152.0119760</gml:pos>
      </gml:Point>
    </caaml:pointLocation>
    <caaml:country>US</caaml:country>
    <caaml:region>AK</caaml:region>
  </caaml:locRef>
  <caaml:snowProfileResultsOf>
    <caaml:SnowProfileMeasurements dir="top down">
      <caaml:metaData/>
      <caaml:profileDepth uom="cm">140</caaml:profileDepth>
      <caaml:weatherCond>
        <caaml:skyCond>SCT</caaml:skyCond>
        <caaml:precipTI>Nil</caaml:precipTI>
        <caaml:airTempPres uom="degC">-5.0</caaml:airTempPres>
      </caaml:weatherCond>
      <caaml:snowPackCond>
        <caaml:hS>
          <caaml:Components>
            <caaml:height uom="cm">140</caaml:height>
          </caaml:Components>
        </caaml:hS>
      </caaml:snowPackCond>
      <caaml:surfCond>
        <caaml:metaData>
          <caaml:customData>
            <snowpilot:windLoading>previous</snowpilot:windLoading>
          </caaml:customData>
        </caaml:metaData>
        <caaml:penetrationFoot uom="cm">60</caaml:penetrationFoot>
        <caaml:penetrationSki uom="cm">25</caaml:penetrationSki>
      </caaml:surfCond>
      <caaml:stratProfile>
        <caaml:Layer>
          <caaml:depthTop uom="cm">0</caaml:depthTop>
          <caaml:thickness uom="cm">39.6</caaml:thickness>
          <caaml:grainFormPrimary>PP</caaml:grainFormPrimary>
          <caaml:hardnessTop uom="">F</caaml:hardnessTop>
          <caaml:hardnessBottom uom="">4F</caaml:hardnessBottom>
        </caaml:Layer>
        <caaml:Layer>
          <caaml:depthTop uom="cm">39.6</caaml:depthTop>
          <caaml:thickness uom="cm">26</caaml:thickness>
          <caaml:grainFormPrimary>DF</caaml:grainFormPrimary>
          <caaml:hardness uom="">4F</caaml:hardness>
        </caaml:Layer>
        <caaml:Layer>
          <caaml:depthTop uom="cm">65.6</caaml:depthTop>
          <caaml:thickness uom="cm">3.8</caaml:thickness>
          <caaml:hardness uom="">1F+</caaml:hardness>
        </caaml:Layer>
        <caaml:Layer>
          <caaml:depthTop uom="cm">69.4</caaml:depthTop>
          <caaml:thickness uom="cm">11</caaml:thickness>
          <caaml:hardnessTop uom="">1F</caaml:hardnessTop>
          <caaml:hardnessBottom uom="">1F</caaml:hardnessBottom>
        </caaml:Layer>
        <caaml:Layer>
          <caaml:depthTop uom="cm">80.4</caaml:depthTop>
          <caaml:thickness uom="cm">19.6</caaml:thickness>
          <caaml:grainFormPrimary>FC</caaml:grainFormPrimary>
          <caaml:hardness uom="">4F</caaml:hardness>
          <caaml:layerOfConcern partOfLayer="">true</caaml:layerOfConcern>
        </caaml:Layer>
        <caaml:Layer>
          <caaml:depthTop uom="cm">100</caaml:depthTop>
          <caaml:thickness uom="cm">40</caaml:thickness>
          <caaml:hardnessTop uom="">1F</caaml:hardnessTop>
          <caaml:hardnessBottom uom="">P</caaml:hardnessBottom>
        </caaml:Layer>
      </caaml:stratProfile>
      <caaml:stbTests>
        <caaml:ExtColumnTest>
          <caaml:noFailure/>
        </caaml:ExtColumnTest>
        <caaml:ComprTest>
          <caaml:failedOn>
            <caaml:Layer>
              <caaml:depthTop uom="cm">65</caaml:depthTop>
            </caaml:Layer>
            <caaml:Results>
              <caaml:fractureCharacter>RP</caaml:fractureCharacter>
              <caaml:testScore>18</caaml:testScore>
            </caaml:Results>
          </caaml:failedOn>
        </caaml:ComprTest>
      </caaml:stbTests>
    </caaml:SnowProfileMeasurements>
  </caaml:snowProfileResultsOf>
  <caaml:application>SnowPilot</caaml:application>
  <caaml:applicationVersion>7.91-0.1</caaml:applicationVersion>
</caaml:SnowProfile>
