<?xml version="1.0" encoding="UTF-8"?>
<caaml:SnowProfile xmlns:caaml="http://caaml.org/Schemas/SnowProfileIACS/v6.0.3" xmlns:gml="http://www.opengis.net/gml" xmlns:snowpilot="http://www.snowpilot.org/Schemas/caaml" gml:id="SnowPilot-64115">
  <caaml:metaData>
    <caaml:comment>Ihålig känsla vid skidåkning uppför vid TL. </caaml:comment>
    <caaml:customData/>
  </caaml:metaData>
  <caaml:timeRef>
    <caaml:recordTime>
      <caaml:TimeInstant>
        <caaml:timePosition>2024-03-18T10:25:00</caaml:timePosition>
      </caaml:TimeInstant>
    </caaml:recordTime>
    <caaml:dateTimeReport>2024-03-18T02:47:59-08:00</caaml:dateTimeReport>
    <caaml:dateTimeLastEdit>2024-03-18T02:50:41-08:00</caaml:dateTimeLastEdit>
  </caaml:timeRef>
  <caaml:srcRef>
    <caaml:Operation gml:id="SnowPilot-Group-263">
      <caaml:name>Acadia Mountain Guides</caaml:name>
      <caaml:contactPerson gml:id="SnowPilot-User-4207">
        <caaml:name>Sam</caaml:name>
      </caaml:contactPerson>
    </caaml:Operation>
  </caaml:srcRef>
  <caaml:locRef gml:id="location-nid-64115">
    <caaml:name>Skreaberget</caaml:name>
    <caaml:obsPointSubType>SnowPilot Snowpit site</caaml:obsPointSubType>
    <caaml:validElevation>
      <caaml:ElevationPosition uom="m">
        <caaml:position>740</caaml:position>
      </caaml:ElevationPosition>
    </caaml:validElevation>
    <caaml:validAspect>
      <caaml:AspectPosition>
        <caaml:position>SE</caaml:position>
      </caaml:AspectPosition>
    </caaml:validAspect>
    <caaml:validSlopeAngle>
      <caaml:SlopeAnglePosition uom="deg">
        <caaml:position>25</caaml:position>
      </caaml:SlopeAnglePosition>
    </caaml:validSlopeAngle>
    <caaml:pointLocation>
      <gml:Point gml:id="pointID" srsDimension="2" srsName="urn:ogc:def:crs:OGC:1.3:CRS84">
        <gml:pos>65.9084040 14.9524780</gml:pos>
      </gml:Point>
    </caaml:pointLocation>
    <caaml:country>SE</caaml:country>
    <caaml:region>Västra Vindelfjällen</caaml:region>
  </caaml:locRef>
  <caaml:snowProfileResultsOf>
    <caaml:SnowProfileMeasurements dir="top down">
      <caaml:metaData/>
      <caaml:profileDepth uom="cm">100</caaml:profileDepth>
      <caaml:weatherCond>
        <caaml:skyCond>BKN</caaml:skyCond>
        <caaml:precipTI>Nil</caaml:precipTI>
        <caaml:airTempPres uom="degC">-5.0</caaml:airTempPres>
        <caaml:windSpd uom="">L</caaml:windSpd>
        <caaml:windDir>
          <caaml:AspectPosition>
            <caaml:position>SE</caaml:position>
          </caaml:AspectPosition>
        </caaml:windDir>
      </caaml:weatherCond>
      <caaml:snowPackCond>
        <caaml:hS>
          <caaml:Components>
            <caaml:height uom="cm">250</caaml:height>
          </caaml:Components>
        </caaml:hS>
      </caaml:snowPackCond>
      <caaml:surfCond>
        <caaml:metaData>
          <caaml:customData>
            <snowpilot:windLoading>no</snowpilot:windLoading>
          </caaml:customData>
        </caaml:metaData>
        <caaml:penetrationFoot uom="cm">20</caaml:penetrationFoot>
      </caaml:surfCond>
      <caaml:stratProfile>
        <caaml:Layer>
          <caaml:depthTop uom="cm">0</caaml:depthTop>
          <caaml:thickness uom="cm">19</caaml:thickness>
          <caaml:grainFormPrimary>RG</caaml:grainFormPrimary>
          <caaml:hardness uom="">P-</caaml:hardness>
        </caaml:Layer>
        <caaml:Layer>
          <caaml:metaData>
            <caaml:comment>Inslag av SH</caaml:comment>
          </caaml:metaData>
          <caaml:depthTop uom="cm">19</caaml:depthTop>
          <caaml:thickness uom="cm">9</caaml:thickness>
          <caaml:grainFormPrimary>DF</caaml:grainFormPrimary>
          <caaml:grainFormSecondary>SH</caaml:grainFormSecondary>
          <caaml:hardness uom="">4F</caaml:hardness>
          <caaml:layerOfConcern partOfLayer="all">true</caaml:layerOfConcern>
        </caaml:Layer>
        <caaml:Layer>
          <caaml:metaData>
            <caaml:comment>Också känsligt</caaml:comment>
          </caaml:metaData>
          <caaml:depthTop uom="cm">28</caaml:depthTop>
          <caaml:thickness uom="cm">2</caaml:thickness>
          <caaml:grainFormPrimary>FCsf</caaml:grainFormPrimary>
          <caaml:hardness uom="">4F+</caaml:hardness>
        </caaml:Layer>
        <caaml:Layer>
          <caaml:depthTop uom="cm">30</caaml:depthTop>
          <caaml:thickness uom="cm">12</caaml:thickness>
          <caaml:hardness uom="">1F</caaml:hardness>
        </caaml:Layer>
        <caaml:Layer>
          <caaml:depthTop uom="cm">42</caaml:depthTop>
          <caaml:thickness uom="cm">58</caaml:thickness>
          <caaml:hardness uom="">P+</caaml:hardness>
        </caaml:Layer>
      </caaml:stratProfile>
      <caaml:tempProfile>
        <caaml:tempMetaData/>
        <caaml:Obs>
          <caaml:depth uom="cm">10</caaml:depth>
          <caaml:snowTemp uom="degC">-8.2</caaml:snowTemp>
        </caaml:Obs>
        <caaml:Obs>
          <caaml:depth uom="cm">20</caaml:depth>
          <caaml:snowTemp uom="degC">-6.2</caaml:snowTemp>
        </caaml:Obs>
        <caaml:Obs>
          <caaml:depth uom="cm">30</caaml:depth>
          <caaml:snowTemp uom="degC">-6.1</caaml:snowTemp>
        </caaml:Obs>
        <caaml:Obs>
          <caaml:depth uom="cm">40</caaml:depth>
          <caaml:snowTemp uom="degC">-5.4</caaml:snowTemp>
        </caaml:Obs>
        <caaml:Obs>
          <caaml:depth uom="cm">50</caaml:depth>
          <caaml:snowTemp uom="degC">-5.1</caaml:snowTemp>
        </caaml:Obs>
        <caaml:Obs>
          <caaml:depth uom="cm">60</caaml:depth>
          <caaml:snowTemp uom="degC">-4.8</caaml:snowTemp>
        </caaml:Obs>
        <caaml:Obs>
          <caaml:depth uom="cm">80</caaml:depth>
          <caaml:snowTemp uom="degC">-4.3</caaml:snowTemp>
        </caaml:Obs>
      </caaml:tempProfile>
      <caaml:stbTests>
        <caaml:ExtColumnTest>
          <caaml:failedOn>
            <caaml:Layer>
              <caaml:depthTop uom="cm">19</caaml:depthTop>
            </caaml:Layer>
            <caaml:Results>
              <caaml:testScore>ECTN12</caaml:testScore>
            </caaml:Results>
          </caaml:failedOn>
        </caaml:ExtColumnTest>
        <caaml:ExtColumnTest>
          <caaml:failedOn>
            <caaml:Layer>
              <caaml:depthTop uom="cm">28</caaml:depthTop>
            </caaml:Layer>
            <caaml:Results>
              <caaml:testScore>ECTN19</caaml:testScore>
            </caaml:Results>
          </caaml:failedOn>
        </caaml:ExtColumnTest>
      </caaml:stbTests>
    </caaml:SnowProfileMeasurements>
  </caaml:snowProfileResultsOf>
  <caaml:application>SnowPilot</caaml:application>
  <caaml:applicationVersion>7.91-0.1</caaml:applicationVersion>
</caaml:SnowProfile>
