<?xml version="1.0" encoding="UTF-8"?>
<caaml:SnowProfile xmlns:caaml="http://caaml.org/Schemas/SnowProfileIACS/v6.0.3" xmlns:gml="http://www.opengis.net/gml" xmlns:snowpilot="http://www.snowpilot.org/Schemas/caaml" gml:id="SnowPilot-1216">
  <caaml:metaData/>
  <caaml:timeRef>
    <caaml:recordTime>
      <caaml:TimeInstant>
        <caaml:timePosition>2017-01-15T10:00:00</caaml:timePosition>
      </caaml:TimeInstant>
    </caaml:recordTime>
    <caaml:dateTimeReport>2017-01-15T18:06:24-09:00</caaml:dateTimeReport>
    <caaml:dateTimeLastEdit>2020-03-12T08:14:52-08:00</caaml:dateTimeLastEdit>
  </caaml:timeRef>
  <caaml:srcRef>
    <caaml:Operation gml:id="SnowPilot-Group-373">
      <caaml:name>UI Outdoor Program</caaml:name>
      <caaml:contactPerson gml:id="SnowPilot-User-4191">
        <caaml:name>tgfulton</caaml:name>
      </caaml:contactPerson>
    </caaml:Operation>
  </caaml:srcRef>
  <caaml:locRef gml:id="location-nid-1216">
    <caaml:name>Bridger Bradley Mead. </caaml:name>
    <caaml:obsPointSubType>SnowPilot Snowpit site</caaml:obsPointSubType>
    <caaml:validElevation>
      <caaml:ElevationPosition uom="m">
        <caaml:position>1875</caaml:position>
      </caaml:ElevationPosition>
    </caaml:validElevation>
    <caaml:validAspect>
      <caaml:AspectPosition>
        <caaml:position>E</caaml:position>
      </caaml:AspectPosition>
    </caaml:validAspect>
    <caaml:validSlopeAngle>
      <caaml:SlopeAnglePosition uom="deg">
        <caaml:position>24</caaml:position>
      </caaml:SlopeAnglePosition>
    </caaml:validSlopeAngle>
    <caaml:country>US</caaml:country>
    <caaml:region>MT</caaml:region>
  </caaml:locRef>
  <caaml:snowProfileResultsOf>
    <caaml:SnowProfileMeasurements dir="top down">
      <caaml:metaData/>
      <caaml:profileDepth uom="cm">100</caaml:profileDepth>
      <caaml:weatherCond>
        <caaml:skyCond>CLR</caaml:skyCond>
        <caaml:precipTI>Nil</caaml:precipTI>
        <caaml:windSpd uom="">M</caaml:windSpd>
        <caaml:windDir>
          <caaml:AspectPosition>
            <caaml:position>W</caaml:position>
          </caaml:AspectPosition>
        </caaml:windDir>
      </caaml:weatherCond>
      <caaml:snowPackCond>
        <caaml:hS>
          <caaml:Components>
            <caaml:height uom="cm">100</caaml:height>
          </caaml:Components>
        </caaml:hS>
      </caaml:snowPackCond>
      <caaml:surfCond>
        <caaml:metaData/>
        <caaml:penetrationFoot uom="cm">70</caaml:penetrationFoot>
        <caaml:customData>
          <snowpilot:windLoading>previous</snowpilot:windLoading>
        </caaml:customData>
      </caaml:surfCond>
      <caaml:stratProfile>
        <caaml:stratMetaData/>
        <caaml:Layer>
          <caaml:depthTop uom="cm">0</caaml:depthTop>
          <caaml:thickness uom="cm">10</caaml:thickness>
          <caaml:grainFormPrimary>DFbk</caaml:grainFormPrimary>
          <caaml:grainSize uom="mm">
            <caaml:Components>
              <caaml:avg>1</caaml:avg>
            </caaml:Components>
          </caaml:grainSize>
          <caaml:hardnessTop uom="">F</caaml:hardnessTop>
          <caaml:hardnessBottom uom="">F</caaml:hardnessBottom>
        </caaml:Layer>
        <caaml:Layer>
          <caaml:depthTop uom="cm">10</caaml:depthTop>
          <caaml:thickness uom="cm">25</caaml:thickness>
          <caaml:grainFormPrimary>RGsr</caaml:grainFormPrimary>
          <caaml:grainSize uom="mm">
            <caaml:Components>
              <caaml:avg>1</caaml:avg>
            </caaml:Components>
          </caaml:grainSize>
          <caaml:hardnessTop uom="">4F</caaml:hardnessTop>
          <caaml:hardnessBottom uom="">4F</caaml:hardnessBottom>
        </caaml:Layer>
        <caaml:Layer>
          <caaml:metaData>
            <caaml:comment>3 Lemons: Top M, Hard, Pers</caaml:comment>
          </caaml:metaData>
          <caaml:depthTop uom="cm">35</caaml:depthTop>
          <caaml:thickness uom="cm">20</caaml:thickness>
          <caaml:grainFormPrimary>FCso</caaml:grainFormPrimary>
          <caaml:grainSize uom="mm">
            <caaml:Components>
              <caaml:avg>1.5</caaml:avg>
            </caaml:Components>
          </caaml:grainSize>
          <caaml:hardness uom="">F+</caaml:hardness>
          <caaml:layerOfConcern partOfLayer="all">true</caaml:layerOfConcern>
        </caaml:Layer>
        <caaml:Layer>
          <caaml:depthTop uom="cm">55</caaml:depthTop>
          <caaml:thickness uom="cm">30</caaml:thickness>
          <caaml:grainFormPrimary>RGxf</caaml:grainFormPrimary>
          <caaml:grainSize uom="mm">
            <caaml:Components>
              <caaml:avg>1</caaml:avg>
            </caaml:Components>
          </caaml:grainSize>
          <caaml:hardness uom="">4F+</caaml:hardness>
        </caaml:Layer>
        <caaml:Layer>
          <caaml:depthTop uom="cm">85</caaml:depthTop>
          <caaml:thickness uom="cm">5</caaml:thickness>
          <caaml:grainFormPrimary>RGlr</caaml:grainFormPrimary>
          <caaml:grainSize uom="mm">
            <caaml:Components>
              <caaml:avg>1</caaml:avg>
            </caaml:Components>
          </caaml:grainSize>
          <caaml:hardness uom="">1F</caaml:hardness>
        </caaml:Layer>
        <caaml:Layer>
          <caaml:depthTop uom="cm">90</caaml:depthTop>
          <caaml:thickness uom="cm">10</caaml:thickness>
          <caaml:grainFormPrimary>FCso</caaml:grainFormPrimary>
          <caaml:grainSize uom="mm">
            <caaml:Components>
              <caaml:avg>3</caaml:avg>
            </caaml:Components>
          </caaml:grainSize>
          <caaml:hardness uom="">F+</caaml:hardness>
        </caaml:Layer>
      </caaml:stratProfile>
      <caaml:stbTests>
        <caaml:ComprTest>
          <caaml:failedOn>
            <caaml:Layer>
              <caaml:depthTop uom="cm">35</caaml:depthTop>
            </caaml:Layer>
            <caaml:Results>
              <caaml:fractureCharacter>Q2</caaml:fractureCharacter>
              <caaml:testScore>20</caaml:testScore>
            </caaml:Results>
          </caaml:failedOn>
        </caaml:ComprTest>
        <caaml:ExtColumnTest>
          <caaml:failedOn>
            <caaml:Layer>
              <caaml:depthTop uom="cm">35</caaml:depthTop>
            </caaml:Layer>
            <caaml:Results>
              <caaml:testScore>ECTN16</caaml:testScore>
            </caaml:Results>
          </caaml:failedOn>
        </caaml:ExtColumnTest>
      </caaml:stbTests>
    </caaml:SnowProfileMeasurements>
  </caaml:snowProfileResultsOf>
  <caaml:application>SnowPilot</caaml:application>
  <caaml:applicationVersion>7.91-0.1</caaml:applicationVersion>
  <caaml:customData>
    <snowpilot:visibility spGroupID="373">group</snowpilot:visibility>
  </caaml:customData>
</caaml:SnowProfile>
