<?xml version="1.0" encoding="UTF-8"?>
<caaml:SnowProfile xmlns:caaml="http://caaml.org/Schemas/SnowProfileIACS/v6.0.3" xmlns:gml="http://www.opengis.net/gml" xmlns:snowpilot="http://www.snowpilot.org/Schemas/caaml" gml:id="SnowPilot-28503">
  <caaml:metaData>
    <caaml:customData/>
  </caaml:metaData>
  <caaml:timeRef>
    <caaml:recordTime>
      <caaml:TimeInstant>
        <caaml:timePosition>2021-01-09T12:00:00</caaml:timePosition>
      </caaml:TimeInstant>
    </caaml:recordTime>
    <caaml:dateTimeReport>2021-01-09T17:51:11-09:00</caaml:dateTimeReport>
    <caaml:dateTimeLastEdit>2021-01-09T17:54:14-09:00</caaml:dateTimeLastEdit>
  </caaml:timeRef>
  <caaml:srcRef>
    <caaml:Operation gml:id="SnowPilot-Group-424">
      <caaml:name>Chugach National Forest Avalanche Center</caaml:name>
      <caaml:contactPerson gml:id="SnowPilot-User-3820">
        <caaml:name>andrewschauer</caaml:name>
      </caaml:contactPerson>
    </caaml:Operation>
  </caaml:srcRef>
  <caaml:locRef gml:id="location-nid-28503">
    <caaml:name>Raggedtop</caaml:name>
    <caaml:obsPointSubType>SnowPilot Snowpit site</caaml:obsPointSubType>
    <caaml:validElevation>
      <caaml:ElevationPosition uom="m">
        <caaml:position>753</caaml:position>
      </caaml:ElevationPosition>
    </caaml:validElevation>
    <caaml:validAspect>
      <caaml:AspectPosition>
        <caaml:position>N</caaml:position>
      </caaml:AspectPosition>
    </caaml:validAspect>
    <caaml:validSlopeAngle>
      <caaml:SlopeAnglePosition uom="deg">
        <caaml:position>32</caaml:position>
      </caaml:SlopeAnglePosition>
    </caaml:validSlopeAngle>
    <caaml:pointLocation>
      <gml:Point gml:id="pointID" srsDimension="2" srsName="urn:ogc:def:crs:OGC:1.3:CRS84">
        <gml:pos>61.0111111 -149.1038889</gml:pos>
      </gml:Point>
    </caaml:pointLocation>
    <caaml:country>US</caaml:country>
    <caaml:region>AK</caaml:region>
  </caaml:locRef>
  <caaml:snowProfileResultsOf>
    <caaml:SnowProfileMeasurements dir="top down">
      <caaml:metaData/>
      <caaml:profileDepth uom="cm">205</caaml:profileDepth>
      <caaml:weatherCond>
        <caaml:skyCond>BKN</caaml:skyCond>
        <caaml:precipTI>-SN</caaml:precipTI>
        <caaml:airTempPres uom="degC">-3.0</caaml:airTempPres>
        <caaml:windSpd uom="">L</caaml:windSpd>
        <caaml:windDir>
          <caaml:AspectPosition>
            <caaml:position>SE</caaml:position>
          </caaml:AspectPosition>
        </caaml:windDir>
      </caaml:weatherCond>
      <caaml:snowPackCond>
        <caaml:hS>
          <caaml:Components>
            <caaml:height uom="cm">205</caaml:height>
          </caaml:Components>
        </caaml:hS>
      </caaml:snowPackCond>
      <caaml:surfCond>
        <caaml:metaData>
          <caaml:customData>
            <snowpilot:windLoading>previous</snowpilot:windLoading>
          </caaml:customData>
        </caaml:metaData>
        <caaml:penetrationFoot uom="cm">90</caaml:penetrationFoot>
        <caaml:penetrationSki uom="cm">30</caaml:penetrationSki>
      </caaml:surfCond>
      <caaml:stratProfile>
        <caaml:Layer>
          <caaml:depthTop uom="cm">0</caaml:depthTop>
          <caaml:thickness uom="cm">42</caaml:thickness>
          <caaml:grainFormPrimary>PP</caaml:grainFormPrimary>
          <caaml:hardness uom="">F-</caaml:hardness>
        </caaml:Layer>
        <caaml:Layer>
          <caaml:depthTop uom="cm">42</caaml:depthTop>
          <caaml:thickness uom="cm">22</caaml:thickness>
          <caaml:grainFormPrimary>DF</caaml:grainFormPrimary>
          <caaml:hardness uom="">4F</caaml:hardness>
        </caaml:Layer>
        <caaml:Layer>
          <caaml:depthTop uom="cm">64</caaml:depthTop>
          <caaml:thickness uom="cm">1</caaml:thickness>
          <caaml:grainFormPrimary>PPsd</caaml:grainFormPrimary>
          <caaml:layerOfConcern partOfLayer="all">true</caaml:layerOfConcern>
        </caaml:Layer>
        <caaml:Layer>
          <caaml:depthTop uom="cm">65</caaml:depthTop>
          <caaml:thickness uom="cm">5</caaml:thickness>
          <caaml:grainFormPrimary>RG</caaml:grainFormPrimary>
          <caaml:grainFormSecondary>FCxr</caaml:grainFormSecondary>
          <caaml:hardness uom="">4F</caaml:hardness>
        </caaml:Layer>
        <caaml:Layer>
          <caaml:depthTop uom="cm">70</caaml:depthTop>
          <caaml:thickness uom="cm">21</caaml:thickness>
          <caaml:grainFormPrimary>RG</caaml:grainFormPrimary>
          <caaml:hardnessTop uom="">4F</caaml:hardnessTop>
          <caaml:hardnessBottom uom="">1F</caaml:hardnessBottom>
        </caaml:Layer>
        <caaml:Layer>
          <caaml:depthTop uom="cm">91</caaml:depthTop>
          <caaml:thickness uom="cm">54</caaml:thickness>
          <caaml:grainFormPrimary>RG</caaml:grainFormPrimary>
          <caaml:hardness uom="">P</caaml:hardness>
        </caaml:Layer>
        <caaml:Layer>
          <caaml:depthTop uom="cm">145</caaml:depthTop>
          <caaml:thickness uom="cm">2</caaml:thickness>
          <caaml:grainFormPrimary>IFrc</caaml:grainFormPrimary>
          <caaml:hardness uom="">P</caaml:hardness>
        </caaml:Layer>
        <caaml:Layer>
          <caaml:depthTop uom="cm">147</caaml:depthTop>
          <caaml:thickness uom="cm">3</caaml:thickness>
          <caaml:grainFormPrimary>MFcl</caaml:grainFormPrimary>
          <caaml:hardness uom="">1F+</caaml:hardness>
        </caaml:Layer>
        <caaml:Layer>
          <caaml:depthTop uom="cm">150</caaml:depthTop>
          <caaml:thickness uom="cm">2</caaml:thickness>
          <caaml:grainFormPrimary>MFcr</caaml:grainFormPrimary>
          <caaml:hardness uom="">P</caaml:hardness>
        </caaml:Layer>
        <caaml:Layer>
          <caaml:depthTop uom="cm">152</caaml:depthTop>
          <caaml:thickness uom="cm">3</caaml:thickness>
          <caaml:grainFormPrimary>MFcl</caaml:grainFormPrimary>
          <caaml:hardness uom="">1F+</caaml:hardness>
        </caaml:Layer>
        <caaml:Layer>
          <caaml:depthTop uom="cm">155</caaml:depthTop>
          <caaml:thickness uom="cm">5</caaml:thickness>
          <caaml:grainFormPrimary>RG</caaml:grainFormPrimary>
          <caaml:hardness uom="">P-</caaml:hardness>
        </caaml:Layer>
      </caaml:stratProfile>
      <caaml:stbTests>
        <caaml:ExtColumnTest>
          <caaml:failedOn>
            <caaml:Layer>
              <caaml:depthTop uom="cm">65</caaml:depthTop>
            </caaml:Layer>
            <caaml:Results>
              <caaml:testScore>ECTP24</caaml:testScore>
            </caaml:Results>
          </caaml:failedOn>
        </caaml:ExtColumnTest>
      </caaml:stbTests>
    </caaml:SnowProfileMeasurements>
  </caaml:snowProfileResultsOf>
  <caaml:application>SnowPilot</caaml:application>
  <caaml:applicationVersion>7.91-0.1</caaml:applicationVersion>
</caaml:SnowProfile>
