<?xml version="1.0" encoding="UTF-8"?>
<caaml:SnowProfile xmlns:caaml="http://caaml.org/Schemas/SnowProfileIACS/v6.0.3" xmlns:gml="http://www.opengis.net/gml" xmlns:snowpilot="http://www.snowpilot.org/Schemas/caaml" gml:id="SnowPilot-74479">
  <caaml:metaData>
    <caaml:comment>brant knix i TL, perfekt ackumulation av drevsnö från v/nv</caaml:comment>
  </caaml:metaData>
  <caaml:timeRef>
    <caaml:recordTime>
      <caaml:TimeInstant>
        <caaml:timePosition>2025-03-19T10:00:00</caaml:timePosition>
      </caaml:TimeInstant>
    </caaml:recordTime>
    <caaml:dateTimeReport>2025-03-19T04:25:20-08:00</caaml:dateTimeReport>
    <caaml:dateTimeLastEdit>2025-03-19T04:25:44-08:00</caaml:dateTimeLastEdit>
  </caaml:timeRef>
  <caaml:srcRef>
    <caaml:Person gml:id="SnowPilot-User-13738">
      <caaml:name>moa almqvist</caaml:name>
    </caaml:Person>
  </caaml:srcRef>
  <caaml:locRef gml:id="location-nid-74479">
    <caaml:name>Kaisepakte tl</caaml:name>
    <caaml:obsPointSubType>SnowPilot Snowpit site</caaml:obsPointSubType>
    <caaml:validElevation>
      <caaml:ElevationPosition uom="m">
        <caaml:position>565</caaml:position>
      </caaml:ElevationPosition>
    </caaml:validElevation>
    <caaml:validAspect>
      <caaml:AspectPosition>
        <caaml:position>E</caaml:position>
      </caaml:AspectPosition>
    </caaml:validAspect>
    <caaml:validSlopeAngle>
      <caaml:SlopeAnglePosition uom="deg">
        <caaml:position>35</caaml:position>
      </caaml:SlopeAnglePosition>
    </caaml:validSlopeAngle>
    <caaml:pointLocation>
      <gml:Point gml:id="pointID" srsDimension="2" srsName="urn:ogc:def:crs:OGC:1.3:CRS84">
        <gml:pos>68.2575190 19.3718150</gml:pos>
      </gml:Point>
    </caaml:pointLocation>
    <caaml:country>SE</caaml:country>
    <caaml:region>Abisko</caaml:region>
  </caaml:locRef>
  <caaml:snowProfileResultsOf>
    <caaml:SnowProfileMeasurements dir="top down">
      <caaml:metaData/>
      <caaml:profileDepth uom="cm">100</caaml:profileDepth>
      <caaml:weatherCond>
        <caaml:skyCond>BKN</caaml:skyCond>
        <caaml:precipTI>-SN</caaml:precipTI>
        <caaml:airTempPres uom="degC">-6.2</caaml:airTempPres>
        <caaml:windSpd uom="">S</caaml:windSpd>
        <caaml:windDir>
          <caaml:AspectPosition>
            <caaml:position>NW</caaml:position>
          </caaml:AspectPosition>
        </caaml:windDir>
      </caaml:weatherCond>
      <caaml:snowPackCond>
        <caaml:hS>
          <caaml:Components>
            <caaml:height uom="cm">270</caaml:height>
          </caaml:Components>
        </caaml:hS>
      </caaml:snowPackCond>
      <caaml:surfCond>
        <caaml:metaData/>
        <caaml:penetrationFoot uom="cm">49</caaml:penetrationFoot>
        <caaml:customData>
          <snowpilot:windLoading>yes</snowpilot:windLoading>
        </caaml:customData>
      </caaml:surfCond>
      <caaml:stratProfile>
        <caaml:stratMetaData/>
        <caaml:Layer>
          <caaml:metaData>
            <caaml:comment>varierande 4F-1F</caaml:comment>
          </caaml:metaData>
          <caaml:depthTop uom="cm">0</caaml:depthTop>
          <caaml:thickness uom="cm">48</caaml:thickness>
          <caaml:grainFormPrimary>DF</caaml:grainFormPrimary>
          <caaml:grainFormSecondary>PP</caaml:grainFormSecondary>
          <caaml:hardness uom="">4F</caaml:hardness>
        </caaml:Layer>
        <caaml:Layer>
          <caaml:metaData>
            <caaml:comment>ev fc</caaml:comment>
          </caaml:metaData>
          <caaml:depthTop uom="cm">48</caaml:depthTop>
          <caaml:thickness uom="cm">2</caaml:thickness>
          <caaml:grainFormPrimary>DF</caaml:grainFormPrimary>
          <caaml:hardness uom="">F</caaml:hardness>
        </caaml:Layer>
        <caaml:Layer>
          <caaml:metaData>
            <caaml:comment>pwl: 18/3</caaml:comment>
          </caaml:metaData>
          <caaml:depthTop uom="cm">50</caaml:depthTop>
          <caaml:thickness uom="cm">0.5</caaml:thickness>
          <caaml:grainFormPrimary>MFcr</caaml:grainFormPrimary>
          <caaml:hardness uom="">P</caaml:hardness>
        </caaml:Layer>
        <caaml:Layer>
          <caaml:depthTop uom="cm">50.5</caaml:depthTop>
          <caaml:thickness uom="cm">2.5</caaml:thickness>
          <caaml:grainFormPrimary>DF</caaml:grainFormPrimary>
          <caaml:hardness uom="">F</caaml:hardness>
        </caaml:Layer>
        <caaml:Layer>
          <caaml:depthTop uom="cm">53</caaml:depthTop>
          <caaml:thickness uom="cm">12</caaml:thickness>
          <caaml:hardness uom="">4F</caaml:hardness>
        </caaml:Layer>
        <caaml:Layer>
          <caaml:depthTop uom="cm">65</caaml:depthTop>
          <caaml:thickness uom="cm">35</caaml:thickness>
          <caaml:hardnessTop uom="">1F</caaml:hardnessTop>
          <caaml:hardnessBottom uom="">P</caaml:hardnessBottom>
        </caaml:Layer>
      </caaml:stratProfile>
      <caaml:tempProfile>
        <caaml:tempMetaData/>
        <caaml:Obs>
          <caaml:depth uom="cm">10</caaml:depth>
          <caaml:snowTemp uom="degC">-6.5</caaml:snowTemp>
        </caaml:Obs>
        <caaml:Obs>
          <caaml:depth uom="cm">20</caaml:depth>
          <caaml:snowTemp uom="degC">-6.5</caaml:snowTemp>
        </caaml:Obs>
        <caaml:Obs>
          <caaml:depth uom="cm">30</caaml:depth>
          <caaml:snowTemp uom="degC">-5.5</caaml:snowTemp>
        </caaml:Obs>
        <caaml:Obs>
          <caaml:depth uom="cm">40</caaml:depth>
          <caaml:snowTemp uom="degC">-4.5</caaml:snowTemp>
        </caaml:Obs>
        <caaml:Obs>
          <caaml:depth uom="cm">50</caaml:depth>
          <caaml:snowTemp uom="degC">-4.0</caaml:snowTemp>
        </caaml:Obs>
      </caaml:tempProfile>
      <caaml:stbTests>
        <caaml:ExtColumnTest>
          <caaml:failedOn>
            <caaml:Layer>
              <caaml:metaData>
                <caaml:comment>på Df/pp</caaml:comment>
              </caaml:metaData>
              <caaml:depthTop uom="cm">9</caaml:depthTop>
            </caaml:Layer>
            <caaml:Results>
              <caaml:testScore>ECTN1</caaml:testScore>
            </caaml:Results>
          </caaml:failedOn>
        </caaml:ExtColumnTest>
        <caaml:ExtColumnTest>
          <caaml:failedOn>
            <caaml:Layer>
              <caaml:metaData>
                <caaml:comment>på df/pp</caaml:comment>
              </caaml:metaData>
              <caaml:depthTop uom="cm">15</caaml:depthTop>
            </caaml:Layer>
            <caaml:Results>
              <caaml:testScore>ECTN2</caaml:testScore>
            </caaml:Results>
          </caaml:failedOn>
        </caaml:ExtColumnTest>
        <caaml:ExtColumnTest>
          <caaml:failedOn>
            <caaml:Layer>
              <caaml:metaData>
                <caaml:comment>på df</caaml:comment>
              </caaml:metaData>
              <caaml:depthTop uom="cm">24</caaml:depthTop>
            </caaml:Layer>
            <caaml:Results>
              <caaml:testScore>ECTP12</caaml:testScore>
            </caaml:Results>
          </caaml:failedOn>
        </caaml:ExtColumnTest>
        <caaml:ExtColumnTest>
          <caaml:failedOn>
            <caaml:Layer>
              <caaml:metaData>
                <caaml:comment>på fc?</caaml:comment>
              </caaml:metaData>
              <caaml:depthTop uom="cm">49</caaml:depthTop>
            </caaml:Layer>
            <caaml:Results>
              <caaml:testScore>ECTN13</caaml:testScore>
            </caaml:Results>
          </caaml:failedOn>
        </caaml:ExtColumnTest>
      </caaml:stbTests>
    </caaml:SnowProfileMeasurements>
  </caaml:snowProfileResultsOf>
  <caaml:application>SnowPilot</caaml:application>
  <caaml:applicationVersion>7.91-0.1</caaml:applicationVersion>
  <caaml:customData>
    <snowpilot:visibility>public</snowpilot:visibility>
  </caaml:customData>
</caaml:SnowProfile>
