<?xml version="1.0" encoding="UTF-8"?>
<caaml:SnowProfile xmlns:caaml="http://caaml.org/Schemas/SnowProfileIACS/v6.0.3" xmlns:gml="http://www.opengis.net/gml" xmlns:snowpilot="http://www.snowpilot.org/Schemas/caaml" gml:id="SnowPilot-37646">
  <caaml:metaData>
    <caaml:customData/>
  </caaml:metaData>
  <caaml:timeRef>
    <caaml:recordTime>
      <caaml:TimeInstant>
        <caaml:timePosition>2022-01-11T13:15:00</caaml:timePosition>
      </caaml:TimeInstant>
    </caaml:recordTime>
    <caaml:dateTimeReport>2022-01-11T14:24:40-09:00</caaml:dateTimeReport>
    <caaml:dateTimeLastEdit>2022-01-11T14:25:03-09:00</caaml:dateTimeLastEdit>
  </caaml:timeRef>
  <caaml:srcRef>
    <caaml:Operation gml:id="SnowPilot-Group-53">
      <caaml:name>Gallatin National Forest Avalanche Center</caaml:name>
      <caaml:contactPerson gml:id="SnowPilot-User-1520">
        <caaml:name>ianhoyer</caaml:name>
      </caaml:contactPerson>
    </caaml:Operation>
  </caaml:srcRef>
  <caaml:locRef gml:id="location-nid-37646">
    <caaml:name>Watkins Creek</caaml:name>
    <caaml:obsPointSubType>SnowPilot Snowpit site</caaml:obsPointSubType>
    <caaml:validElevation>
      <caaml:ElevationPosition uom="m">
        <caaml:position>2686</caaml:position>
      </caaml:ElevationPosition>
    </caaml:validElevation>
    <caaml:validAspect>
      <caaml:AspectPosition>
        <caaml:position>NE</caaml:position>
      </caaml:AspectPosition>
    </caaml:validAspect>
    <caaml:validSlopeAngle>
      <caaml:SlopeAnglePosition uom="deg">
        <caaml:position>38</caaml:position>
      </caaml:SlopeAnglePosition>
    </caaml:validSlopeAngle>
    <caaml:pointLocation>
      <gml:Point gml:id="pointID" srsDimension="2" srsName="urn:ogc:def:crs:OGC:1.3:CRS84">
        <gml:pos>44.7340670 -111.3476530</gml:pos>
      </gml:Point>
    </caaml:pointLocation>
    <caaml:country>US</caaml:country>
    <caaml:region>MT</caaml:region>
  </caaml:locRef>
  <caaml:snowProfileResultsOf>
    <caaml:SnowProfileMeasurements dir="top down">
      <caaml:metaData/>
      <caaml:profileDepth uom="cm">160</caaml:profileDepth>
      <caaml:weatherCond>
        <caaml:skyCond>OVC</caaml:skyCond>
        <caaml:precipTI>Nil</caaml:precipTI>
        <caaml:windSpd uom="">C</caaml:windSpd>
      </caaml:weatherCond>
      <caaml:snowPackCond>
        <caaml:hS>
          <caaml:Components>
            <caaml:height uom="cm">160</caaml:height>
          </caaml:Components>
        </caaml:hS>
      </caaml:snowPackCond>
      <caaml:surfCond>
        <caaml:metaData>
          <caaml:customData>
            <snowpilot:windLoading>no</snowpilot:windLoading>
          </caaml:customData>
        </caaml:metaData>
        <caaml:penetrationFoot uom="cm">50</caaml:penetrationFoot>
      </caaml:surfCond>
      <caaml:stratProfile>
        <caaml:Layer>
          <caaml:depthTop uom="cm">0</caaml:depthTop>
          <caaml:thickness uom="cm">2</caaml:thickness>
          <caaml:grainFormPrimary>RGwp</caaml:grainFormPrimary>
          <caaml:hardness uom="">4F</caaml:hardness>
        </caaml:Layer>
        <caaml:Layer>
          <caaml:depthTop uom="cm">2</caaml:depthTop>
          <caaml:thickness uom="cm">18</caaml:thickness>
          <caaml:grainFormPrimary>PP</caaml:grainFormPrimary>
          <caaml:hardness uom="">F+</caaml:hardness>
        </caaml:Layer>
        <caaml:Layer>
          <caaml:depthTop uom="cm">20</caaml:depthTop>
          <caaml:thickness uom="cm">57</caaml:thickness>
          <caaml:grainFormPrimary>RG</caaml:grainFormPrimary>
          <caaml:hardness uom="">1F</caaml:hardness>
        </caaml:Layer>
        <caaml:Layer>
          <caaml:depthTop uom="cm">77</caaml:depthTop>
          <caaml:thickness uom="cm">23</caaml:thickness>
          <caaml:grainFormPrimary>FCxr</caaml:grainFormPrimary>
          <caaml:grainSize uom="mm">
            <caaml:Components>
              <caaml:avg>1</caaml:avg>
            </caaml:Components>
          </caaml:grainSize>
          <caaml:hardness uom="">1F</caaml:hardness>
        </caaml:Layer>
        <caaml:Layer>
          <caaml:depthTop uom="cm">100</caaml:depthTop>
          <caaml:thickness uom="cm">25</caaml:thickness>
          <caaml:grainFormPrimary>FC</caaml:grainFormPrimary>
          <caaml:grainSize uom="mm">
            <caaml:Components>
              <caaml:avg>2</caaml:avg>
            </caaml:Components>
          </caaml:grainSize>
          <caaml:hardness uom="">4F+</caaml:hardness>
        </caaml:Layer>
        <caaml:Layer>
          <caaml:depthTop uom="cm">125</caaml:depthTop>
          <caaml:thickness uom="cm">5</caaml:thickness>
          <caaml:grainFormPrimary>DH</caaml:grainFormPrimary>
          <caaml:grainSize uom="mm">
            <caaml:Components>
              <caaml:avg>2</caaml:avg>
              <caaml:avgMax>4</caaml:avgMax>
            </caaml:Components>
          </caaml:grainSize>
          <caaml:hardness uom="">F+</caaml:hardness>
          <caaml:layerOfConcern partOfLayer="all">true</caaml:layerOfConcern>
        </caaml:Layer>
        <caaml:Layer>
          <caaml:depthTop uom="cm">130</caaml:depthTop>
          <caaml:thickness uom="cm">10</caaml:thickness>
          <caaml:grainFormPrimary>DH</caaml:grainFormPrimary>
          <caaml:grainSize uom="mm">
            <caaml:Components>
              <caaml:avg>2</caaml:avg>
              <caaml:avgMax>4</caaml:avgMax>
            </caaml:Components>
          </caaml:grainSize>
          <caaml:hardness uom="">1F</caaml:hardness>
        </caaml:Layer>
        <caaml:Layer>
          <caaml:depthTop uom="cm">140</caaml:depthTop>
          <caaml:thickness uom="cm">20</caaml:thickness>
          <caaml:grainFormPrimary>MFcr</caaml:grainFormPrimary>
          <caaml:grainFormSecondary>FC</caaml:grainFormSecondary>
          <caaml:hardnessTop uom="">1F+</caaml:hardnessTop>
          <caaml:hardnessBottom uom="">P</caaml:hardnessBottom>
        </caaml:Layer>
      </caaml:stratProfile>
      <caaml:stbTests>
        <caaml:ExtColumnTest>
          <caaml:failedOn>
            <caaml:Layer>
              <caaml:depthTop uom="cm">125</caaml:depthTop>
            </caaml:Layer>
            <caaml:Results>
              <caaml:testScore>ECTP24</caaml:testScore>
            </caaml:Results>
          </caaml:failedOn>
        </caaml:ExtColumnTest>
      </caaml:stbTests>
    </caaml:SnowProfileMeasurements>
  </caaml:snowProfileResultsOf>
  <caaml:application>SnowPilot</caaml:application>
  <caaml:applicationVersion>7.91-0.1</caaml:applicationVersion>
</caaml:SnowProfile>
