<?xml version="1.0" encoding="UTF-8"?>
<caaml:SnowProfile xmlns:caaml="http://caaml.org/Schemas/SnowProfileIACS/v6.0.3" xmlns:gml="http://www.opengis.net/gml" xmlns:snowpilot="http://www.snowpilot.org/Schemas/caaml" gml:id="SnowPilot-22088">
  <caaml:metaData>
    <caaml:comment>Standard location, Iknouk RAWS</caaml:comment>
    <caaml:customData/>
  </caaml:metaData>
  <caaml:timeRef>
    <caaml:recordTime>
      <caaml:TimeInstant>
        <caaml:timePosition>2020-01-07T10:00:00</caaml:timePosition>
      </caaml:TimeInstant>
    </caaml:recordTime>
    <caaml:dateTimeReport>2020-02-10T10:09:59-09:00</caaml:dateTimeReport>
    <caaml:dateTimeLastEdit>2020-02-10T10:31:43-09:00</caaml:dateTimeLastEdit>
  </caaml:timeRef>
  <caaml:srcRef>
    <caaml:Person gml:id="SnowPilot-User-9368">
      <caaml:name>Mitch Suliak</caaml:name>
    </caaml:Person>
  </caaml:srcRef>
  <caaml:locRef gml:id="location-nid-22088">
    <caaml:name>2020-01-07 Iknouk</caaml:name>
    <caaml:obsPointSubType>SnowPilot Snowpit site</caaml:obsPointSubType>
    <caaml:validElevation>
      <caaml:ElevationPosition uom="m">
        <caaml:position>860</caaml:position>
      </caaml:ElevationPosition>
    </caaml:validElevation>
    <caaml:validAspect>
      <caaml:AspectPosition>
        <caaml:position>S</caaml:position>
      </caaml:AspectPosition>
    </caaml:validAspect>
    <caaml:validSlopeAngle>
      <caaml:SlopeAnglePosition uom="deg">
        <caaml:position>25</caaml:position>
      </caaml:SlopeAnglePosition>
    </caaml:validSlopeAngle>
    <caaml:pointLocation>
      <gml:Point gml:id="pointID" srsDimension="2" srsName="urn:ogc:def:crs:OGC:1.3:CRS84">
        <gml:pos>55.0106740 -129.7748850</gml:pos>
      </gml:Point>
    </caaml:pointLocation>
    <caaml:country>CA</caaml:country>
    <caaml:region>BC</caaml:region>
  </caaml:locRef>
  <caaml:snowProfileResultsOf>
    <caaml:SnowProfileMeasurements dir="top down">
      <caaml:metaData/>
      <caaml:profileDepth uom="cm">173</caaml:profileDepth>
      <caaml:weatherCond>
        <caaml:skyCond>FEW</caaml:skyCond>
        <caaml:precipTI>Nil</caaml:precipTI>
        <caaml:airTempPres uom="degC">-8.0</caaml:airTempPres>
        <caaml:windSpd uom="">L</caaml:windSpd>
        <caaml:windDir>
          <caaml:AspectPosition>
            <caaml:position>E</caaml:position>
          </caaml:AspectPosition>
        </caaml:windDir>
      </caaml:weatherCond>
      <caaml:snowPackCond>
        <caaml:hS>
          <caaml:Components>
            <caaml:height uom="cm">173</caaml:height>
          </caaml:Components>
        </caaml:hS>
      </caaml:snowPackCond>
      <caaml:surfCond>
        <caaml:metaData>
          <caaml:customData>
            <snowpilot:windLoading>no</snowpilot:windLoading>
          </caaml:customData>
        </caaml:metaData>
        <caaml:penetrationFoot uom="cm">80</caaml:penetrationFoot>
      </caaml:surfCond>
      <caaml:stratProfile>
        <caaml:Layer>
          <caaml:depthTop uom="cm">0</caaml:depthTop>
          <caaml:thickness uom="cm">18</caaml:thickness>
          <caaml:hardness uom="">F</caaml:hardness>
          <caaml:wetness uom="">D</caaml:wetness>
        </caaml:Layer>
        <caaml:Layer>
          <caaml:depthTop uom="cm">18</caaml:depthTop>
          <caaml:thickness uom="cm">12</caaml:thickness>
          <caaml:hardness uom="">F+</caaml:hardness>
          <caaml:wetness uom="">D</caaml:wetness>
        </caaml:Layer>
        <caaml:Layer>
          <caaml:depthTop uom="cm">30</caaml:depthTop>
          <caaml:thickness uom="cm">57</caaml:thickness>
          <caaml:hardnessTop uom="">4F</caaml:hardnessTop>
          <caaml:hardnessBottom uom="">1F</caaml:hardnessBottom>
          <caaml:wetness uom="">D</caaml:wetness>
        </caaml:Layer>
        <caaml:Layer>
          <caaml:depthTop uom="cm">87</caaml:depthTop>
          <caaml:thickness uom="cm">6</caaml:thickness>
          <caaml:hardness uom="">P-</caaml:hardness>
          <caaml:wetness uom="">D</caaml:wetness>
        </caaml:Layer>
        <caaml:Layer>
          <caaml:metaData>
            <caaml:comment>Lam CR/FC combo, 200101</caaml:comment>
          </caaml:metaData>
          <caaml:depthTop uom="cm">93</caaml:depthTop>
          <caaml:thickness uom="cm">10</caaml:thickness>
          <caaml:grainFormPrimary>MFcr</caaml:grainFormPrimary>
          <caaml:grainFormSecondary>FCxr</caaml:grainFormSecondary>
          <caaml:grainSize uom="mm">
            <caaml:Components>
              <caaml:avg>3</caaml:avg>
              <caaml:avgMax>5</caaml:avgMax>
            </caaml:Components>
          </caaml:grainSize>
          <caaml:hardness uom="">P</caaml:hardness>
          <caaml:wetness uom="">D</caaml:wetness>
          <caaml:layerOfConcern partOfLayer="all">true</caaml:layerOfConcern>
        </caaml:Layer>
        <caaml:Layer>
          <caaml:depthTop uom="cm">103</caaml:depthTop>
          <caaml:thickness uom="cm">18</caaml:thickness>
          <caaml:hardness uom="">1F</caaml:hardness>
          <caaml:wetness uom="">D</caaml:wetness>
        </caaml:Layer>
        <caaml:Layer>
          <caaml:depthTop uom="cm">121</caaml:depthTop>
          <caaml:thickness uom="cm">1</caaml:thickness>
          <caaml:grainFormPrimary>MFcr</caaml:grainFormPrimary>
          <caaml:hardness uom="">P+</caaml:hardness>
          <caaml:wetness uom="">D</caaml:wetness>
        </caaml:Layer>
        <caaml:Layer>
          <caaml:depthTop uom="cm">122</caaml:depthTop>
          <caaml:thickness uom="cm">10</caaml:thickness>
          <caaml:hardness uom="">P</caaml:hardness>
          <caaml:wetness uom="">D</caaml:wetness>
        </caaml:Layer>
        <caaml:Layer>
          <caaml:depthTop uom="cm">132</caaml:depthTop>
          <caaml:thickness uom="cm">1</caaml:thickness>
          <caaml:grainFormPrimary>MFcr</caaml:grainFormPrimary>
          <caaml:hardness uom="">P+</caaml:hardness>
          <caaml:wetness uom="">D</caaml:wetness>
        </caaml:Layer>
        <caaml:Layer>
          <caaml:depthTop uom="cm">133</caaml:depthTop>
          <caaml:thickness uom="cm">40</caaml:thickness>
          <caaml:hardness uom="">P</caaml:hardness>
          <caaml:wetness uom="">M</caaml:wetness>
        </caaml:Layer>
      </caaml:stratProfile>
      <caaml:tempProfile>
        <caaml:tempMetaData/>
        <caaml:Obs>
          <caaml:depth uom="cm">10</caaml:depth>
          <caaml:snowTemp uom="degC">-8.0</caaml:snowTemp>
        </caaml:Obs>
        <caaml:Obs>
          <caaml:depth uom="cm">23</caaml:depth>
          <caaml:snowTemp uom="degC">-7.5</caaml:snowTemp>
        </caaml:Obs>
        <caaml:Obs>
          <caaml:depth uom="cm">33</caaml:depth>
          <caaml:snowTemp uom="degC">-6.5</caaml:snowTemp>
        </caaml:Obs>
        <caaml:Obs>
          <caaml:depth uom="cm">43</caaml:depth>
          <caaml:snowTemp uom="degC">-5.5</caaml:snowTemp>
        </caaml:Obs>
        <caaml:Obs>
          <caaml:depth uom="cm">53</caaml:depth>
          <caaml:snowTemp uom="degC">-5.0</caaml:snowTemp>
        </caaml:Obs>
        <caaml:Obs>
          <caaml:depth uom="cm">63</caaml:depth>
          <caaml:snowTemp uom="degC">-4.0</caaml:snowTemp>
        </caaml:Obs>
        <caaml:Obs>
          <caaml:depth uom="cm">73</caaml:depth>
          <caaml:snowTemp uom="degC">-4.0</caaml:snowTemp>
        </caaml:Obs>
        <caaml:Obs>
          <caaml:depth uom="cm">83</caaml:depth>
          <caaml:snowTemp uom="degC">-3.0</caaml:snowTemp>
        </caaml:Obs>
        <caaml:Obs>
          <caaml:depth uom="cm">93</caaml:depth>
          <caaml:snowTemp uom="degC">-3.0</caaml:snowTemp>
        </caaml:Obs>
        <caaml:Obs>
          <caaml:depth uom="cm">103</caaml:depth>
          <caaml:snowTemp uom="degC">-2.0</caaml:snowTemp>
        </caaml:Obs>
        <caaml:Obs>
          <caaml:depth uom="cm">113</caaml:depth>
          <caaml:snowTemp uom="degC">-1.5</caaml:snowTemp>
        </caaml:Obs>
        <caaml:Obs>
          <caaml:depth uom="cm">123</caaml:depth>
          <caaml:snowTemp uom="degC">-1.0</caaml:snowTemp>
        </caaml:Obs>
        <caaml:Obs>
          <caaml:depth uom="cm">133</caaml:depth>
          <caaml:snowTemp uom="degC">-1.0</caaml:snowTemp>
        </caaml:Obs>
        <caaml:Obs>
          <caaml:depth uom="cm">143</caaml:depth>
          <caaml:snowTemp uom="degC">-0.5</caaml:snowTemp>
        </caaml:Obs>
        <caaml:Obs>
          <caaml:depth uom="cm">153</caaml:depth>
          <caaml:snowTemp uom="degC">0.0</caaml:snowTemp>
        </caaml:Obs>
      </caaml:tempProfile>
      <caaml:stbTests>
        <caaml:ComprTest>
          <caaml:failedOn>
            <caaml:Layer>
              <caaml:depthTop uom="cm">18</caaml:depthTop>
            </caaml:Layer>
            <caaml:Results>
              <caaml:fractureCharacter>RP</caaml:fractureCharacter>
              <caaml:testScore>16</caaml:testScore>
            </caaml:Results>
          </caaml:failedOn>
        </caaml:ComprTest>
        <caaml:ComprTest>
          <caaml:failedOn>
            <caaml:Layer>
              <caaml:metaData>
                <caaml:comment>HST intrfc.</caaml:comment>
              </caaml:metaData>
              <caaml:depthTop uom="cm">43</caaml:depthTop>
            </caaml:Layer>
            <caaml:Results>
              <caaml:fractureCharacter>RP</caaml:fractureCharacter>
              <caaml:testScore>10</caaml:testScore>
            </caaml:Results>
          </caaml:failedOn>
        </caaml:ComprTest>
        <caaml:ComprTest>
          <caaml:failedOn>
            <caaml:Layer>
              <caaml:metaData>
                <caaml:comment>SC within lams</caaml:comment>
              </caaml:metaData>
              <caaml:depthTop uom="cm">98</caaml:depthTop>
            </caaml:Layer>
            <caaml:Results>
              <caaml:fractureCharacter>SC</caaml:fractureCharacter>
              <caaml:testScore>19</caaml:testScore>
            </caaml:Results>
          </caaml:failedOn>
        </caaml:ComprTest>
      </caaml:stbTests>
    </caaml:SnowProfileMeasurements>
  </caaml:snowProfileResultsOf>
  <caaml:application>SnowPilot</caaml:application>
  <caaml:applicationVersion>7.91-0.1</caaml:applicationVersion>
</caaml:SnowProfile>
