<?xml version="1.0" encoding="UTF-8"?>
<caaml:SnowProfile xmlns:caaml="http://caaml.org/Schemas/SnowProfileIACS/v6.0.3" xmlns:gml="http://www.opengis.net/gml" xmlns:snowpilot="http://www.snowpilot.org/Schemas/caaml" gml:id="SnowPilot-58811">
  <caaml:metaData>
    <caaml:comment>Crown profile on lower skier's left of SZ. Average crown depth 60-70cm, Maximum 80cm.&#13;
SS-ASu-R3-D2-O. Average SZ Angle ~38 degrees. High angle track with MANY trees along its entirety. Snow was entrained from the track to the JAN 4 layer most of the track.  Cracks propagated far into lower angle terrain to skiers left at 7700'. Calculated Runout Angle 31 deg.&#13;
Not much tree damage - this path is a frequent runner. Flow height up to 2.5 meters above bed surface.&#13;
Patient Location: 7370' 43.53311,-111.05651&#13;
Toe: 7230'  43.53292,-111.05556</caaml:comment>
    <caaml:customData>
      <snowpilot:whumpfData>
        <snowpilot:whumpfCracking>true</snowpilot:whumpfCracking>
        <snowpilot:whumpfNoCracking>false</snowpilot:whumpfNoCracking>
        <snowpilot:crackingNoWhumpf>false</snowpilot:crackingNoWhumpf>
        <snowpilot:whumpfNearPit>true</snowpilot:whumpfNearPit>
        <snowpilot:whumpfDepthWeakLayer>true</snowpilot:whumpfDepthWeakLayer>
        <snowpilot:whumpfTriggeredRemoteAva>false</snowpilot:whumpfTriggeredRemoteAva>
        <snowpilot:whumpfSize>terrain-feature</snowpilot:whumpfSize>
      </snowpilot:whumpfData>
    </caaml:customData>
  </caaml:metaData>
  <caaml:timeRef>
    <caaml:recordTime>
      <caaml:TimeInstant>
        <caaml:timePosition>2024-01-13T16:00:00</caaml:timePosition>
      </caaml:TimeInstant>
    </caaml:recordTime>
    <caaml:dateTimeReport>2024-01-14T08:28:37-09:00</caaml:dateTimeReport>
    <caaml:dateTimeLastEdit>2024-01-14T08:32:33-09:00</caaml:dateTimeLastEdit>
  </caaml:timeRef>
  <caaml:srcRef>
    <caaml:Person gml:id="SnowPilot-User-5032">
      <caaml:name>dsharaf</caaml:name>
    </caaml:Person>
  </caaml:srcRef>
  <caaml:locRef gml:id="location-nid-58811">
    <caaml:name>StatelineAv.20240112</caaml:name>
    <caaml:obsPointSubType>SnowPilot Snowpit site</caaml:obsPointSubType>
    <caaml:validElevation>
      <caaml:ElevationPosition uom="m">
        <caaml:position>2420</caaml:position>
      </caaml:ElevationPosition>
    </caaml:validElevation>
    <caaml:validAspect>
      <caaml:AspectPosition>
        <caaml:position>E</caaml:position>
      </caaml:AspectPosition>
    </caaml:validAspect>
    <caaml:validSlopeAngle>
      <caaml:SlopeAnglePosition uom="deg">
        <caaml:position>36</caaml:position>
      </caaml:SlopeAnglePosition>
    </caaml:validSlopeAngle>
    <caaml:pointLocation>
      <gml:Point gml:id="pointID" srsDimension="2" srsName="urn:ogc:def:crs:OGC:1.3:CRS84">
        <gml:pos>43.5331700 -111.0594600</gml:pos>
      </gml:Point>
    </caaml:pointLocation>
    <caaml:country>US</caaml:country>
    <caaml:region>ID</caaml:region>
    <snowpilot:pitNearAvalanche location="crown">true</snowpilot:pitNearAvalanche>
  </caaml:locRef>
  <caaml:snowProfileResultsOf>
    <caaml:SnowProfileMeasurements dir="top down">
      <caaml:metaData/>
      <caaml:profileDepth uom="cm">125</caaml:profileDepth>
      <caaml:weatherCond>
        <caaml:skyCond>OVC</caaml:skyCond>
        <caaml:precipTI>Nil</caaml:precipTI>
        <caaml:airTempPres uom="degC">-16.0</caaml:airTempPres>
        <caaml:windSpd uom="">C</caaml:windSpd>
      </caaml:weatherCond>
      <caaml:snowPackCond>
        <caaml:hS>
          <caaml:Components>
            <caaml:height uom="cm">125</caaml:height>
          </caaml:Components>
        </caaml:hS>
      </caaml:snowPackCond>
      <caaml:surfCond>
        <caaml:metaData>
          <caaml:customData>
            <snowpilot:windLoading>no</snowpilot:windLoading>
          </caaml:customData>
        </caaml:metaData>
        <caaml:penetrationFoot uom="cm">60</caaml:penetrationFoot>
        <caaml:penetrationSki uom="cm">35</caaml:penetrationSki>
      </caaml:surfCond>
      <caaml:stratProfile>
        <caaml:Layer>
          <caaml:depthTop uom="cm">0</caaml:depthTop>
          <caaml:thickness uom="cm">38</caaml:thickness>
          <caaml:grainFormPrimary>DF</caaml:grainFormPrimary>
          <caaml:grainSize uom="mm">
            <caaml:Components>
              <caaml:avg>0.5</caaml:avg>
              <caaml:avgMax>1</caaml:avgMax>
            </caaml:Components>
          </caaml:grainSize>
          <caaml:hardness uom="">F</caaml:hardness>
        </caaml:Layer>
        <caaml:Layer>
          <caaml:depthTop uom="cm">38</caaml:depthTop>
          <caaml:thickness uom="cm">41</caaml:thickness>
          <caaml:grainFormPrimary>DF</caaml:grainFormPrimary>
          <caaml:grainFormSecondary>PP</caaml:grainFormSecondary>
          <caaml:grainSize uom="mm">
            <caaml:Components>
              <caaml:avg>1</caaml:avg>
            </caaml:Components>
          </caaml:grainSize>
          <caaml:hardness uom="">4F</caaml:hardness>
        </caaml:Layer>
        <caaml:Layer>
          <caaml:metaData>
            <caaml:comment>Decomposing Crust</caaml:comment>
          </caaml:metaData>
          <caaml:depthTop uom="cm">79</caaml:depthTop>
          <caaml:thickness uom="cm">3</caaml:thickness>
          <caaml:grainFormPrimary>FC</caaml:grainFormPrimary>
          <caaml:grainSize uom="mm">
            <caaml:Components>
              <caaml:avg>2</caaml:avg>
              <caaml:avgMax>3</caaml:avgMax>
            </caaml:Components>
          </caaml:grainSize>
          <caaml:hardness uom="">4F-</caaml:hardness>
          <caaml:layerOfConcern partOfLayer="top">true</caaml:layerOfConcern>
        </caaml:Layer>
        <caaml:Layer>
          <caaml:metaData>
            <caaml:comment>some rounding-THICK layer</caaml:comment>
          </caaml:metaData>
          <caaml:depthTop uom="cm">82</caaml:depthTop>
          <caaml:thickness uom="cm">23</caaml:thickness>
          <caaml:grainFormPrimary>FC</caaml:grainFormPrimary>
          <caaml:hardness uom="">F</caaml:hardness>
        </caaml:Layer>
        <caaml:Layer>
          <caaml:depthTop uom="cm">105</caaml:depthTop>
          <caaml:thickness uom="cm">20</caaml:thickness>
          <caaml:grainFormPrimary>FCxr</caaml:grainFormPrimary>
          <caaml:grainSize uom="mm">
            <caaml:Components>
              <caaml:avg>1</caaml:avg>
              <caaml:avgMax>1.5</caaml:avgMax>
            </caaml:Components>
          </caaml:grainSize>
          <caaml:hardness uom="">1F</caaml:hardness>
          <caaml:wetness uom="">M</caaml:wetness>
        </caaml:Layer>
      </caaml:stratProfile>
      <caaml:stbTests>
        <caaml:ExtColumnTest>
          <caaml:failedOn>
            <caaml:Layer>
              <caaml:metaData>
                <caaml:comment>SP</caaml:comment>
              </caaml:metaData>
              <caaml:depthTop uom="cm">79</caaml:depthTop>
            </caaml:Layer>
            <caaml:Results>
              <caaml:testScore>ECTP13</caaml:testScore>
            </caaml:Results>
          </caaml:failedOn>
        </caaml:ExtColumnTest>
      </caaml:stbTests>
    </caaml:SnowProfileMeasurements>
  </caaml:snowProfileResultsOf>
  <caaml:application>SnowPilot</caaml:application>
  <caaml:applicationVersion>7.91-0.1</caaml:applicationVersion>
</caaml:SnowProfile>
